History.txt
LICENCE.txt
MANIFEST.in
README.rst
To_Do.txt
setup.py
pyPlotPecube/__init__.py
pyPlotPecube/pyPlotPecubeForward.py
pyPlotPecube/pyPlotPecubeNA.py
pyPlotPecube.egg-info/PKG-INFO
pyPlotPecube.egg-info/SOURCES.txt
pyPlotPecube.egg-info/dependency_links.txt
pyPlotPecube.egg-info/not-zip-safe
pyPlotPecube.egg-info/requires.txt
pyPlotPecube.egg-info/top_level.txt